{
  "slug": "/green-style-tolix-stool-xavier-pauchard",
  "title": "Tolix Stool 31 CM",
  "body": "\r\nDiscover what metals can do with Xavier Pauchard&rsquo;s Tolix Chair. Designed in 1934 to grace the decks of the S.S. Normandie ocean liner. This chair features a stackable design for convenient rearranging and storage. Suitable for commercial use, having passed load-testing requirements and been approved for heavy domestic, general office, and hospitality use. Use it in your dining table or living space for a casual-chic look.",
  "JSON": "{\n  \"type\": \"variant\",\n  \"handle\": \"green-style-tolix-stool-xavier-pauchard\",\n  \"data\": {\n    \"productId\": \"prod_01GPR3XKA9267SR8ZMYQGCJW17\",\n    \"productHandle\": \"style-tolix-stool-xavier-pauchard\",\n    \"hadnleId\": \"variant_01GPR3XKBBZ8G137CRHCSWDHE2\",\n    \"variantHandle\": \"green-style-tolix-stool-xavier-pauchard\"\n  }\n}"
}