{
  "slug": "/style-hans-wegner-ch33-chair-black-leather-soaped-oak",
  "title": "CH33 Chair Black/Soaped - Oak",
  "body": "This Mobelaris style CH33 Chair reminiscent of the classics of the 1950's and 1960's by designer Hans Wegner. Inspired by traditional forms that have shaped CH33 Chair to a timeless chair, which today as well as back then thrills with quality and a classical design language.",
  "JSON": "{\n  \"type\": \"variant\",\n  \"handle\": \"style-hans-wegner-ch33-chair-black-leather-soaped-oak\",\n  \"data\": {\n    \"productId\": \"prod_01GPR3WBVCWT0QKY83BPEDMJXZ\",\n    \"productHandle\": \"style-hans-wegner-ch33-chair-black-leather\",\n    \"hadnleId\": \"variant_01GPR3WBW0YF4PH63NARQ1D2NB\",\n    \"variantHandle\": \"style-hans-wegner-ch33-chair-black-leather-soaped-oak\"\n  }\n}"
}