{
  "slug": "/style-njord-pendant-lamp-inspired-by-mobelaris",
  "title": "Njord Pendant Lamp  ",
  "body": "This Njord Pendant Lamp is look like a simple and yet elegant, the ceiling lamp makes a dramatic addition to a variety of room settings.&nbsp;",
  "JSON": "{\n  \"type\": \"product\",\n  \"handle\": \"style-njord-pendant-lamp-inspired-by-mobelaris\",\n  \"data\": {\n    \"productId\": \"prod_01GPR3WJDTZRZ2V6NSPX7J08YY\",\n    \"productHandle\": \"style-njord-pendant-lamp-inspired-by-mobelaris\"\n  }\n}"
}